README.md
README.rst
setup.py
iterm2_dwim/__init__.py
iterm2_dwim/logger.py
iterm2_dwim/settings.py
iterm2_dwim.egg-info/PKG-INFO
iterm2_dwim.egg-info/SOURCES.txt
iterm2_dwim.egg-info/dependency_links.txt
iterm2_dwim.egg-info/entry_points.txt
iterm2_dwim.egg-info/not-zip-safe
iterm2_dwim.egg-info/top_level.txt
iterm2_dwim/editors/__init__.py
iterm2_dwim/editors/base.py
iterm2_dwim/editors/emacs.py
iterm2_dwim/editors/pycharm.py
iterm2_dwim/editors/sublime.py
iterm2_dwim/parsers/__init__.py
iterm2_dwim/parsers/parsers.py