Metadata-Version: 1.0
Name: iterm2-dwim
Version: 0.0.3
Summary: iTerm2 click handler
Home-page: https://github.com/dandavison/iterm2-dwim
Author: Dan Davison
Author-email: dandavison7@gmail.com
License: UNKNOWN
Platform: UNKNOWN
